Workbook

Sheet Cover
B2: TEST CASE
B3: Version: | C3: 1
B4: Issue date: | C4: 46310
B6: Project Name: | C6: TechStore - Website bán hàng đồ công nghệ
B7: Project Code: | C7: TECHSTORE
B10: Record of change:
B11: Effective Date | C11: Version | D11: Change location | E11: Change description | F11: Originator | G11: Reviewer/ Approver | H11: Reference
B12: 46310 | C12: 1 | D12: All modules | E12: Tạo bộ test case cho toàn bộ website TechStore | F12: Nhóm TechStore | G12: Test Leader | H12: Test Plan TechStore

Sheet TechStore Test Cases
A1: TEST CASE
A3: System Name: | B3: TechStore
A4: Module Code: | B4: TS-ALL - E-commerce website
A5: Test requirement: | B5: Functional, UI/UX, security, database và compatibility
A6: Pass | B6: =COUNTIF(I12:I216,"Pass") -> 179 | C6: Pending | D6: =COUNTIF(I12:I216,"Pending") -> 0
A7: Fail | B7: =COUNTIF(I12:I216,"Fail") -> 9 | C7: Number of test cases: | D7: =COUNTA(A12:A216)-17 -> 188
A9: ID | B9: Test Case Description | C9: Test Case Procedure | D9: Expected Output | H9: Test date | I9: Result | J9: Note
A12: 5.1. Hệ thống và điều hướng
A13: SYS-01 | B13: Mở / và /home. | C13: 1. Mở TechStore trên môi trường test. 2. Không đăng nhập, trừ khi test case yêu cầu vai trò cụ thể. 3. Thực hiện: Mở / và /home. 4. Ghi nhận UI, HTTP response, log và dữ liệu database liên quan. | D13: Vào được trang chủ, HTTP 200, không lỗi font/ảnh. | H13: 46310 | I13: Pass | J13: Ưu tiên: P1 HTTP probe: / và /home đều HTTP 200; main.css HTTP 200 (63.586 byte); trang khai báo UTF-8.
A14: SYS-02 | B14: Mở /health khi SQL Server hoạt động. | C14: 1. Mở TechStore trên môi trường test. 2. Không đăng nhập, trừ khi test case yêu cầu vai trò cụ thể. 3. Thực hiện: Mở /health khi SQL Server hoạt động. 4. Ghi nhận UI, HTTP response, log và dữ liệu database liên quan. | D14: Báo ứng dụng và database hoạt động. | H14: 46310 | I14: Pass | J14: Ưu tiên: P0 Tomcat sạch trả /health HTTP 200; bộ integration sử dụng SQL Server hoàn tất 36/36 kiểm tra.
A15: SYS-03 | B15: Tắt database rồi mở /health và /home, sau đó bật lại. | C15: 1. Mở TechStore trên môi trường test. 2. Không đăng nhập, trừ khi test case yêu cầu vai trò cụ thể. 3. Thực hiện: Tắt database rồi mở /health và /home, sau đó bật lại. 4. Ghi nhận UI, HTTP response, log và dữ liệu database liên quan. | D15: Health báo lỗi có kiểm soát; trang không lộ stack trace/mật khẩu. | H15: 46310 | I15: Pass | J15: Ưu tiên: P1 Batch 1/3 - 15/10/2026 - Pass: Fault-injection trên Tomcat cô lập với DB không truy cập được: /health HTTP 200 báo “Chưa kết nối”, /home HTTP 200 hiển thị cảnh báo có kiểm soát; UI không lộ password, stack trace hoặc exception nội bộ.
A16: SYS-04 | B16: Mở URL không tồn tại. | C16: 1. Mở TechStore trên môi trường test. 2. Không đăng nhập, trừ khi test case yêu cầu vai trò cụ thể. 3. Thực hiện: Mở URL không tồn tại. 4. Ghi nhận UI, HTTP response, log và dữ liệu database liên quan. | D16: HTTP 404 và trang lỗi đúng layout. | H16: 46310 | I16: Pass | J16: Ưu tiên: P1 URL không tồn tại trả HTTP 404 và hiển thị trang lỗi có mã 404.
A17: SYS-05 | B17: Mở trực tiếp /WEB-INF/views/home.jsp. | C17: 1. Mở TechStore trên môi trường test. 2. Không đăng nhập, trừ khi test case yêu cầu vai trò cụ thể. 3. Thực hiện: Mở trực tiếp /WEB-INF/views/home.jsp. 4. Ghi nhận UI, HTTP response, log và dữ liệu database liên quan. | D17: Không truy cập trực tiếp được JSP. | H17: 46310 | I17: Pass | J17: Ưu tiên: P1 Truy cập trực tiếp /WEB-INF/views/home.jsp trả HTTP 404.
A18: SYS-06 | B18: Đi qua logo, header, menu danh mục, footer, Back/Forward. | C18: 1. Mở TechStore trên môi trường test. 2. Không đăng nhập, trừ khi test case yêu cầu vai trò cụ thể. 3. Thực hiện: Đi qua logo, header, menu danh mục, footer, Back/Forward. 4. Ghi nhận UI, HTTP response, log và dữ liệu database liên quan. | D18: URL, trạng thái menu và lịch sử trình duyệt đúng. | H18: 46310 | I18: Pass | J18: Ưu tiên: P2 Batch 1/3 - 15/10/2026 - Pass: logo=/TechStore/home; back=http://localhost:8080/TechStore/home; forward=http://localhost:8080/TechStore/products; header/footer=1/1
A19: 5.2. Đăng ký, đăng nhập và session
A20: AUTH-01 | B20: Đăng ký với dữ liệu hợp lệ. | C20: 1. Mở TechStore trên môi trường test. 2. Chuẩn bị tài khoản và dữ liệu authentication theo nội dung test case. 3. Thực hiện: Đăng ký với dữ liệu hợp lệ. 4. Ghi nhận UI, HTTP response, log và dữ liệu database liên quan. | D20: Tạo CUSTOMER/ACTIVE, mật khẩu không lưu dạng rõ, chuyển đến đăng nhập. | H20: 46310 | I20: Pass | J20: Ưu tiên: P0 Integration test đăng ký thành công, chuyển đến /login; SQL kiểm tra 3/3 mật khẩu đang lưu dạng BCrypt.
A21: AUTH-02 | B21: Nhập email có chữ hoa và khoảng trắng. | C21: 1. Mở TechStore trên môi trường test. 2. Chuẩn bị tài khoản và dữ liệu authentication theo nội dung test case. 3. Thực hiện: Nhập email có chữ hoa và khoảng trắng. 4. Ghi nhận UI, HTTP response, log và dữ liệu database liên quan. | D21: Email được trim, lưu chữ thường và đăng nhập được. | H21: 46310 | I21: Pass | J21: Ưu tiên: P1 Batch 1/3 - 15/10/2026 - Pass: DB normalized email/phone/nameLength=codex.batch1.20261015092634.upper@techstore.local|0901234567|16; login=http://localhost:8080/TechStore/home
A22: AUTH-03 | B22: Thử email sai định dạng và email dài quá giới hạn. | C22: 1. Mở TechStore trên môi trường test. 2. Chuẩn bị tài khoản và dữ liệu authentication theo nội dung test case. 3. Thực hiện: Thử email sai định dạng và email dài quá giới hạn. 4. Ghi nhận UI, HTTP response, log và dữ liệu database liên quan. | D22: Hiển thị lỗi, không tạo user. | H22: 46310 | I22: Pass | J22: Ưu tiên: P1 Batch 1/3 - 15/10/2026 - Pass: rows=0; invalid/long validation=true/true
A23: AUTH-04 | B23: Đăng ký lại email đã tồn tại, kể cả khác hoa/thường. | C23: 1. Mở TechStore trên môi trường test. 2. Chuẩn bị tài khoản và dữ liệu authentication theo nội dung test case. 3. Thực hiện: Đăng ký lại email đã tồn tại, kể cả khác hoa/thường. 4. Ghi nhận UI, HTTP response, log và dữ liệu database liên quan. | D23: Bị từ chối, không tạo bản ghi trùng. | H23: 46310 | I23: Pass | J23: Ưu tiên: P0 Integration test từ chối email trùng; database không tạo thêm bản ghi.
A24: AUTH-05 | B24: Thử họ tên rỗng và dài hơn 150 ký tự. | C24: 1. Mở TechStore trên môi trường test. 2. Chuẩn bị tài khoản và dữ liệu authentication theo nội dung test case. 3. Thực hiện: Thử họ tên rỗng và dài hơn 150 ký tự. 4. Ghi nhận UI, HTTP response, log và dữ liệu database liên quan. | D24: Bị từ chối, giữ dữ liệu form hợp lý. | H24: 46310 | I24: Pass | J24: Ưu tiên: P1 Batch 1/3 - 15/10/2026 - Pass: rows=0
A25: AUTH-06 | B25: Thử số điện thoại 090..., định dạng +84, có dấu cách/gạch và số sai. | C25: 1. Mở TechStore trên môi trường test. 2. Chuẩn bị tài khoản và dữ liệu authentication theo nội dung test case. 3. Thực hiện: Thử số điện thoại 090..., định dạng +84, có dấu cách/gạch và số sai. 4. Ghi nhận UI, HTTP response, log và dữ liệu database liên quan. | D25: Chuẩn hóa số hợp lệ; từ chối số không đủ 10 chữ số/bắt đầu sai. | H25: 46310 | I25: Pass | J25: Ưu tiên: P1 Batch 1/3 - 15/10/2026 - Pass: p090:0901234567; p84:0901234567; pspace:0901234567; pinvalid:rejected
A26: AUTH-07 | B26: Thử mật khẩu 7, 8, 72, 73 ký tự và xác nhận không khớp. | C26: 1. Mở TechStore trên môi trường test. 2. Chuẩn bị tài khoản và dữ liệu authentication theo nội dung test case. 3. Thực hiện: Thử mật khẩu 7, 8, 72, 73 ký tự và xác nhận không khớp. 4. Ghi nhận UI, HTTP response, log và dữ liệu database liên quan. | D26: Chỉ 8–72 ký tự và xác nhận đúng được chấp nhận. | H26: 46310 | I26: Pass | J26: Ưu tiên: P0 Batch 1/3 - 15/10/2026 - Pass: 7:0; 8:1; 72:1; 73:0; mismatch:0
A27: AUTH-08 | B27: Đăng nhập đúng/sai mật khẩu và email không tồn tại. | C27: 1. Mở TechStore trên môi trường test. 2. Chuẩn bị tài khoản và dữ liệu authentication theo nội dung test case. 3. Thực hiện: Đăng nhập đúng/sai mật khẩu và email không tồn tại. 4. Ghi nhận UI, HTTP response, log và dữ liệu database liên quan. | D27: Đúng thì tạo session; sai dùng thông báo chung, không lộ nguyên nhân. | H27: 46310 | I27: Pass | J27: Ưu tiên: P0 Integration test đăng nhập đúng tạo session và mật khẩu sai bị từ chối bằng thông báo chung.
A28: AUTH-09 | B28: Khóa user rồi thử đăng nhập. | C28: 1. Mở TechStore trên môi trường test. 2. Chuẩn bị tài khoản và dữ liệu authentication theo nội dung test case. 3. Thực hiện: Khóa user rồi thử đăng nhập. 4. Ghi nhận UI, HTTP response, log và dữ liệu database liên quan. | D28: Không đăng nhập được. | H28: 46310 | I28: Pass | J28: Ưu tiên: P0 Batch 1/3 - 15/10/2026 - Pass: loginUrl=http://localhost:8080/TechStore/login; error=true
A29: AUTH-10 | B29: Mở /cart khi chưa đăng nhập, sau đó đăng nhập. | C29: 1. Mở TechStore trên môi trường test. 2. Chuẩn bị tài khoản và dữ liệu authentication theo nội dung test case. 3. Thực hiện: Mở /cart khi chưa đăng nhập, sau đó đăng nhập. 4. Ghi nhận UI, HTTP response, log và dữ liệu database liên quan. | D29: Chuyển về /cart; không mất query string ở URL đã lưu. | H29: 46310 | I29: Pass | J29: Ưu tiên: P1 Batch 1/3 - 15/10/2026 - Pass: redirect=http://localhost:8080/TechStore/cart?source=batch1
A30: AUTH-11 | B30: Đăng nhập admin từ trang login bình thường. | C30: 1. Mở TechStore trên môi trường test. 2. Chuẩn bị tài khoản và dữ liệu authentication theo nội dung test case. 3. Thực hiện: Đăng nhập admin từ trang login bình thường. 4. Ghi nhận UI, HTTP response, log và dữ liệu database liên quan. | D30: Chuyển thẳng đến /admin. | H30: 46310 | I30: Pass | J30: Ưu tiên: P0 Tài khoản test được gán ADMIN, đăng nhập thành công và mở được /admin cùng bốn trang quản trị, đều HTTP 200.
A31: AUTH-12 | B31: Khách cố mở /admin; người chưa login mở /admin. | C31: 1. Mở TechStore trên môi trường test. 2. Chuẩn bị tài khoản và dữ liệu authentication theo nội dung test case. 3. Thực hiện: Khách cố mở /admin; người chưa login mở /admin. 4. Ghi nhận UI, HTTP response, log và dữ liệu database liên quan. | D31: Khách nhận 403; người chưa login chuyển login rồi về admin nếu đăng nhập admin. | H31: 46310 | I31: Pass | J31: Ưu tiên: P0 CUSTOMER nhận HTTP 403 tại admin; người chưa đăng nhập nhận HTTP 302 về /login; ADMIN truy cập được sau đăng nhập.
... A34: AUTH-15 | B34: Không thao tác 30 phút rồi truy cập trang bảo vệ. | C34: 1. Mở TechStore trên môi trường test. 2. Chuẩn bị tài khoản và dữ liệu authentication theo nội dung test case. 3. Thực hiện: Không thao tác 30 phút rồi truy cập trang bảo vệ. 4. Ghi nhận UI, HTTP response, log và dữ liệu database liên quan. | D34: Session hết hạn và yêu cầu đăng nhập lại. | H34: 46310 | I34: Pass | J34: Ưu tiên: P1 Batch 1/3 - 15/10/2026 - Pass: Đối chiếu web.xml session-timeout=30 phút và chạy Tomcat StandardSession với idle 31 phút: session bị invalid, trang bảo vệ sẽ yêu cầu đăng nhập lại.
A35: 5.3. Quên và đặt lại mật khẩu
A36: RESET-01 | B36: Gửi email tồn tại, không tồn tại và sai định dạng. | C36: 1. Mở TechStore trên môi trường test. 2. Chuẩn bị tài khoản và dữ liệu authentication theo nội dung test case. 3. Thực hiện: Gửi email tồn tại, không tồn tại và sai định dạng. 4. Ghi nhận UI, HTTP response, log và dữ liệu database liên quan. | D36: Giao diện luôn trả cùng thông báo chung. | H36: 46310 | I36: Pass | J36: Ưu tiên: P1 Batch 1/3 - 15/10/2026 - Pass: generic response present=true/true/true
A37: RESET-02 | B37: Kiểm tra email reset của tài khoản active. | C37: 1. Mở TechStore trên môi trường test. 2. Chuẩn bị tài khoản và dữ liệu authentication theo nội dung test case. 3. Thực hiện: Kiểm tra email reset của tài khoản active. 4. Ghi nhận UI, HTTP response, log và dữ liệu database liên quan. | D37: Link dùng đúng app.url, có token; database chỉ lưu hash, không lưu token thô. | H37: 46310 | I37: Pass | J37: Ưu tiên: P0 Batch 1/3 - 15/10/2026 - Pass: mail=true; app.url=true; tokenLength=43; DB stores matching SHA-256 only=true
A38: RESET-03 | B38: Dùng token hợp lệ đổi mật khẩu 8–72 ký tự. | C38: 1. Mở TechStore trên môi trường test. 2. Chuẩn bị tài khoản và dữ liệu authentication theo nội dung test case. 3. Thực hiện: Dùng token hợp lệ đổi mật khẩu 8–72 ký tự. 4. Ghi nhận UI, HTTP response, log và dữ liệu database liên quan. | D38: Đổi thành công; mật khẩu cũ thất bại, mật khẩu mới đăng nhập được. | H38: 46310 | I38: Pass | J38: Ưu tiên: P0 Batch 1/3 - 15/10/2026 - Pass: old/new login=http://localhost:8080/TechStore/login/http://localhost:8080/TechStore/home; used=1
A39: RESET-04 | B39: Dùng lại token đã dùng. | C39: 1. Mở TechStore trên môi trường test. 2. Chuẩn bị tài khoản và dữ liệu authentication theo nội dung test case. 3. Thực hiện: Dùng lại token đã dùng. 4. Ghi nhận UI, HTTP response, log và dữ liệu database liên quan. | D39: Bị từ chối. | H39: 46310 | I39: Pass | J39: Ưu tiên: P0 Batch 1/3 - 15/10/2026 - Pass: reuse rejected=true
A40: RESET-05 | B40: Dùng token sai, rỗng, quá 200 ký tự hoặc token quá 30 phút. | C40: 1. Mở TechStore trên môi trường test. 2. Chuẩn bị tài khoản và dữ liệu authentication theo nội dung test case. 3. Thực hiện: Dùng token sai, rỗng, quá 200 ký tự hoặc token quá 30 phút. 4. Ghi nhận UI, HTTP response, log và dữ liệu database liên quan. | D40: Bị từ chối bằng thông báo an toàn. | H40: 46310 | I40: Pass | J40: Ưu tiên: P0 Batch 1/3 - 15/10/2026 - Pass: HTTP đã từ chối token sai, rỗng và dài 201 ký tự; focused production-service probe xác nhận đủ 4/4 trường hợp, gồm token hết hạn do DAO trả consume=false.
A41: RESET-06 | B41: Yêu cầu link mới khi link cũ còn hiệu lực. | C41: 1. Mở TechStore trên môi trường test. 2. Chuẩn bị tài khoản và dữ liệu authentication theo nội dung test case. 3. Thực hiện: Yêu cầu link mới khi link cũ còn hiệu lực. 4. Ghi nhận UI, HTTP response, log và dữ liệu database liên quan. | D41: Token active cũ bị thay thế/không còn dùng được. | H41: 46310 | I41: Pass | J41: Ưu tiên: P1 Batch 1/3 - 15/10/2026 - Pass: active|oldInvalidated=1|1
A42: RESET-07 | B42: Gửi 4 lần trong 15 phút cho cùng tài khoản. | C42: 1. Mở TechStore trên môi trường test. 2. Chuẩn bị tài khoản và dữ liệu authentication theo nội dung test case. 3. Thực hiện: Gửi 4 lần trong 15 phút cho cùng tài khoản. 4. Ghi nhận UI, HTTP response, log và dữ liệu database liên quan. | D42: Tối đa 3 yêu cầu được tạo/gửi; phản hồi không lộ việc bị giới hạn. | H42: 46310 | I42: Pass | J42: Ưu tiên: P1 Batch 1/3 - 15/10/2026 - Pass: Đã gửi 4 request HTTP; truy vấn ban đầu dùng SYSDATETIME local trong khi Hibernate lưu UTC nên đếm sai. Focused service probe với cùng rate-window xác nhận chỉ 3/4 token được tạo.
A43: RESET-08 | B43: Gỡ cấu hình mail và thử gửi. | C43: 1. Mở TechStore trên môi trường test. 2. Chuẩn bị tài khoản và dữ liệu authentication theo nội dung test case. 3. Thực hiện: Gỡ cấu hình mail và thử gửi. 4. Ghi nhận UI, HTTP response, log và dữ liệu database liên quan. | D43: Không lộ mật khẩu/stack trace ra UI; token thất bại được vô hiệu hóa. | H43: 46310 | I43: Pass | J43: Ưu tiên: P1 Batch 1/3 - 15/10/2026 - Pass: Chạy PasswordResetServiceImpl không có TECHSTORE_MAIL_*: token SHA-256 được tạo rồi invalidate; exception an toàn, không chứa tên biến mật khẩu. ForgotPasswordServlet dùng thông báo chung và không đưa stack trace ra UI.
A44: 5.4. Trang chủ, catalog và chi tiết sản phẩm
A45: CAT-01 | B45: Mở trang chủ với dữ liệu mẫu. | C45: 1. Mở TechStore trên môi trường test. 2. Không đăng nhập, trừ khi test case yêu cầu vai trò cụ thể. 3. Thực hiện: Mở trang chủ với dữ liệu mẫu. 4. Ghi nhận UI, HTTP response, log và dữ liệu database liên quan. | D45: Hiển thị tối đa 8 sản phẩm mới và tối đa 4 sản phẩm mỗi danh mục có dữ liệu. | H45: 46310 | I45: Pass | J45: Ưu tiên: P1 Batch 1/3 - 15/10/2026 - Pass: Trang chủ hiển thị 8 sản phẩm mới; 4 section danh mục lần lượt 4,4,4,4 sản phẩm. Selector ban đầu đếm nhầm block featured thêm một lần.
A46: CAT-02 | B46: Tìm theo tên/từ khóa tiếng Việt, hoa/thường và từ không tồn tại. | C46: 1. Mở TechStore trên môi trường test. 2. Không đăng nhập, trừ khi test case yêu cầu vai trò cụ thể. 3. Thực hiện: Tìm theo tên/từ khóa tiếng Việt, hoa/thường và từ không tồn tại. 4. Ghi nhận UI, HTTP response, log và dữ liệu database liên quan. | D46: Kết quả đúng; trường hợp rỗng có thông báo phù hợp. | H46: 46310 | I46: Pass | J46: Ưu tiên: P1 Batch 1/3 - 15/10/2026 - Pass: keyword=Laptop; lower/upper=10/10; emptyState=1
A47: CAT-03 | B47: Lọc riêng và kết hợp danh mục, hãng, giá min/max. | C47: 1. Mở TechStore trên môi trường test. 2. Không đăng nhập, trừ khi test case yêu cầu vai trò cụ thể. 3. Thực hiện: Lọc riêng và kết hợp danh mục, hãng, giá min/max. 4. Ghi nhận UI, HTTP response, log và dữ liệu database liên quan. | D47: Chỉ hiện sản phẩm phù hợp và giữ filter trong URL. | H47: 46310 | I47: Pass | J47: Ưu tiên: P1 Batch 1/3 - 15/10/2026 - Pass: cards=2; url=http://localhost:8080/TechStore/products?categoryId=5&brandId=19&minPrice=500000&maxPrice=3000000&sort=price_asc
A48: CAT-04 | B48: Nhập giá âm, min lớn hơn max, chuỗi thay cho số. | C48: 1. Mở TechStore trên môi trường test. 2. Không đăng nhập, trừ khi test case yêu cầu vai trò cụ thể. 3. Thực hiện: Nhập giá âm, min lớn hơn max, chuỗi thay cho số. 4. Ghi nhận UI, HTTP response, log và dữ liệu database liên quan. | D48: Không lỗi 500; báo dữ liệu lọc không hợp lệ. | H48: 46310 | I48: Fail | J48: Ưu tiên: P1 Batch 1/3 - 15/10/2026 - Fail: minPrice=-1 và minPrice>maxPrice không bị validation từ chối; minPrice=abc chỉ hiện thông báo chung về kết nối SQL thay vì lỗi dữ liệu lọc. Không có HTTP 500 nhưng chưa đúng expected result.
A49: CAT-05 | B49: Sắp xếp mới nhất, giá tăng, giá giảm trên nhiều trang. | C49: 1. Mở TechStore trên môi trường test. 2. Không đăng nhập, trừ khi test case yêu cầu vai trò cụ thể. 3. Thực hiện: Sắp xếp mới nhất, giá tăng, giá giảm trên nhiều trang. 4. Ghi nhận UI, HTTP response, log và dữ liệu database liên quan. | D49: Thứ tự đúng và không mất filter khi đổi trang. | H49: 46310 | I49: Pass | J49: Ưu tiên: P1 Batch 1/3 - 15/10/2026 - Pass: latest:true/24;price_asc:true/24;price_desc:true/24
A50: CAT-06 | B50: Thử page 0, âm, rất lớn và không phải số. | C50: 1. Mở TechStore trên môi trường test. 2. Không đăng nhập, trừ khi test case yêu cầu vai trò cụ thể. 3. Thực hiện: Thử page 0, âm, rất lớn và không phải số. 4. Ghi nhận UI, HTTP response, log và dữ liệu database liên quan. | D50: Chuẩn hóa hoặc hiển thị an toàn, không lỗi 500. | H50: 46310 | I50: Pass | J50: Ưu tiên: P1 Batch 1/3 - 15/10/2026 - Pass: 0:200;-2:200;999999:200;abc:200
A51: CAT-07 | B51: Mở chi tiết sản phẩm active bằng slug hợp lệ. | C51: 1. Mở TechStore trên môi trường test. 2. Không đăng nhập, trừ khi test case yêu cầu vai trò cụ thể. 3. Thực hiện: Mở chi tiết sản phẩm active bằng slug hợp lệ. 4. Ghi nhận UI, HTTP response, log và dữ liệu database liên quan. | D51: Ảnh, phiên bản, giá, tồn, mô tả, thông số và liên quan đúng. | H51: 46310 | I51: Pass | J51: Ưu tiên: P1 Batch 1/3 - 15/10/2026 - Pass: {"img":1,"variant":1,"price":1,"desc":1,"spec":5,"related":4}
A52: CAT-08 | B52: Mở slug sai, sản phẩm DRAFT/INACTIVE. | C52: 1. Mở TechStore trên môi trường test. 2. Không đăng nhập, trừ khi test case yêu cầu vai trò cụ thể. 3. Thực hiện: Mở slug sai, sản phẩm DRAFT/INACTIVE. 4. Ghi nhận UI, HTTP response, log và dữ liệu database liên quan. | D52: HTTP 404; sản phẩm ẩn không xuất hiện trong catalog. | H52: 46310 | I52: Pass | J52: Ưu tiên: P0 Batch 1/3 - 15/10/2026 - Pass: bad=404; hidden=404; listed=false
A53: CAT-09 | B53: Chọn từng phiên bản. | C53: 1. Mở TechStore trên môi trường test. 2. Không đăng nhập, trừ khi test case yêu cầu vai trò cụ thể. 3. Thực hiện: Chọn từng phiên bản. 4. Ghi nhận UI, HTTP response, log và dữ liệu database liên quan. | D53: Giá, giá gốc, giảm giá, tồn kho và ảnh đổi đúng. | H53: 46310 | I53: Pass | J53: Ưu tiên: P1 Batch 1/3 - 15/10/2026 - Pass: 1000000/1000000,stock=5/5;2000000/2000000,stock=3/3
A54: CAT-10 | B54: Sản phẩm không ảnh/không thông số/không biến thể khả dụng. | C54: 1. Mở TechStore trên môi trường test. 2. Không đăng nhập, trừ khi test case yêu cầu vai trò cụ thể. 3. Thực hiện: Sản phẩm không ảnh/không thông số/không biến thể khả dụng. 4. Ghi nhận UI, HTTP response, log và dữ liệu database liên quan. | D54: Có placeholder/trạng thái rỗng; nút mua bị vô hiệu đúng. | H54: 46310 | I54: Pass | J54: Ưu tiên: P1 Batch 1/3 - 15/10/2026 - Pass: placeholder=/TechStore/assets/images/product-placeholder.svg; contact=true; disabled=true; emptySpec=true
A55: CAT-11 | B55: Phiên bản tồn kho 0 hoặc ngừng bán. | C55: 1. Mở TechStore trên môi trường test. 2. Không đăng nhập, trừ khi test case yêu cầu vai trò cụ thể. 3. Thực hiện: Phiên bản tồn kho 0 hoặc ngừng bán. 4. Ghi nhận UI, HTTP response, log và dữ liệu database liên quan. | D55: Không thể thêm vào giỏ dù sửa request thủ công. | H55: 46310 | I55: Pass | J55: Ưu tiên: P1 Batch 1/3 - 15/10/2026 - Pass: inactive/out-of-stock variants blocked=true
A56: CAT-12 | B56: Kiểm tra ký tự HTML/script trong tên/mô tả dữ liệu test. | C56: 1. Mở TechStore trên môi trường test. 2. Không đăng nhập, trừ khi test case yêu cầu vai trò cụ thể. 3. Thực hiện: Kiểm tra ký tự HTML/script trong tên/mô tả dữ liệu test. 4. Ghi nhận UI, HTTP response, log và dữ liệu database liên quan. | D56: Nội dung được escape, script không chạy. | H56: 46310 | I56: Pass | J56: Ưu tiên: P2 Batch 1/3 - 15/10/2026 - Pass: dialogs=0; marker=0; h1=<script>window.__techstoreXss=1</script>
A57: 5.5. Yêu thích
A58: FAV-01 | B58: Chưa đăng nhập bấm yêu thích. | C58: 1. Mở TechStore trên môi trường test. 2. Đăng nhập bằng tài khoản CUSTOMER phù hợp; với VNPay dùng sandbox. 3. Thực hiện: Chưa đăng nhập bấm yêu thích. 4. Ghi nhận UI, HTTP response, log và dữ liệu database liên quan. | D58: Chuyển đến login. | H58: 46310 | I58: Pass | J58: Ưu tiên: P1 HTTP probe khi chưa đăng nhập trả 302 về /login.
A59: FAV-02 | B59: Thêm một sản phẩm từ card/chi tiết. | C59: 1. Mở TechStore trên môi trường test. 2. Đăng nhập bằng tài khoản CUSTOMER phù hợp; với VNPay dùng sandbox. 3. Thực hiện: Thêm một sản phẩm từ card/chi tiết. 4. Ghi nhận UI, HTTP response, log và dữ liệu database liên quan. | D59: Có đúng một dòng favorite; icon/count/header cập nhật. | H59: 46310 | I59: Pass | J59: Ưu tiên: P1 Integration test thêm favorite thành công; SQL xác nhận đúng 1 bản ghi và trang favorites render đúng.
A60: FAV-03 | B60: Bấm lại cùng sản phẩm. | C60: 1. Mở TechStore trên môi trường test. 2. Đăng nhập bằng tài khoản CUSTOMER phù hợp; với VNPay dùng sandbox. 3. Thực hiện: Bấm lại cùng sản phẩm. 4. Ghi nhận UI, HTTP response, log và dữ liệu database liên quan. | D60: Bỏ yêu thích, không có bản ghi trùng. | H60: 46310 | I60: Pass | J60: Ưu tiên: P1 Batch 1/3 - 15/10/2026 - Pass: rows after double toggle=0
A61: FAV-04 | B61: Trang yêu thích rỗng và có nhiều sản phẩm. | C61: 1. Mở TechStore trên môi trường test. 2. Đăng nhập bằng tài khoản CUSTOMER phù hợp; với VNPay dùng sandbox. 3. Thực hiện: Trang yêu thích rỗng và có nhiều sản phẩm. 4. Ghi nhận UI, HTTP response, log và dữ liệu database liên quan. | D61: Empty state/card hiển thị đúng. | H61: 46310 | I61: Pass | J61: Ưu tiên: P1 Batch 1/3 - 15/10/2026 - Pass: empty=true; cards=2
A62: FAV-05 | B62: Sửa productId không tồn tại hoặc gửi favorite của user khác. | C62: 1. Mở TechStore trên môi trường test. 2. Đăng nhập bằng tài khoản CUSTOMER phù hợp; với VNPay dùng sandbox. 3. Thực hiện: Sửa productId không tồn tại hoặc gửi favorite của user khác. 4. Ghi nhận UI, HTTP response, log và dữ liệu database liên quan. | D62: Không lỗi dữ liệu, không tác động tài khoản khác. | H62: 46310 | I62: Fail | J62: Ưu tiên: P0 Batch 1/3 - 15/10/2026 - Fail: HTTP=500; controlled=false; userB=0->0
A63: 5.6. Giỏ hàng
A64: CART-01 | B64: Thêm một phiên bản với số lượng hợp lệ. | C64: 1. Mở TechStore trên môi trường test. 2. Đăng nhập bằng tài khoản CUSTOMER phù hợp; với VNPay dùng sandbox. 3. Thực hiện: Thêm một phiên bản với số lượng hợp lệ. 4. Ghi nhận UI, HTTP response, log và dữ liệu database liên quan. | D64: Tạo giỏ active/dòng giỏ, count header và tổng tiền đúng. | H64: 46310 | I64: Pass | J64: Ưu tiên: P1 Integration test thêm phiên bản hợp lệ; giỏ render HTTP 200 và dữ liệu giỏ được tạo.
A65: CART-02 | B65: Thêm lại cùng SKU nhiều lần. | C65: 1. Mở TechStore trên môi trường test. 2. Đăng nhập bằng tài khoản CUSTOMER phù hợp; với VNPay dùng sandbox. 3. Thực hiện: Thêm lại cùng SKU nhiều lần. 4. Ghi nhận UI, HTTP response, log và dữ liệu database liên quan. | D65: Gộp một dòng và cộng số lượng. | H65: 46310 | I65: Pass | J65: Ưu tiên: P1 Thêm cùng SKU hai lần; SQL xác nhận 1 dòng với Quantity = 2.
A66: CART-03 | B66: Thêm/cập nhật số lượng 0, âm, chữ, vượt tồn kho. | C66: 1. Mở TechStore trên môi trường test. 2. Đăng nhập bằng tài khoản CUSTOMER phù hợp; với VNPay dùng sandbox. 3. Thực hiện: Thêm/cập nhật số lượng 0, âm, chữ, vượt tồn kho. 4. Ghi nhận UI, HTTP response, log và dữ liệu database liên quan. | D66: Bị từ chối; dữ liệu cũ không đổi. | H66: 46310 | I66: Pass | J66: Ưu tiên: P0 Batch 1/3 - 15/10/2026 - Pass: 0:1;-1:1;abc:1;99:1
A67: CART-04 | B67: Thêm biến thể inactive, sản phẩm inactive hoặc ID không tồn tại. | C67: 1. Mở TechStore trên môi trường test. 2. Đăng nhập bằng tài khoản CUSTOMER phù hợp; với VNPay dùng sandbox. 3. Thực hiện: Thêm biến thể inactive, sản phẩm inactive hoặc ID không tồn tại. 4. Ghi nhận UI, HTTP response, log và dữ liệu database liên quan. | D67: Bị từ chối phía server. | H67: 46310 | I67: Pass | J67: Ưu tiên: P0 Batch 1/3 - 15/10/2026 - Pass: inactive product/variant/nonexistent blocked=true
A68: CART-05 | B68: Cập nhật tăng/giảm số lượng bằng nút và nhập trực tiếp. | C68: 1. Mở TechStore trên môi trường test. 2. Đăng nhập bằng tài khoản CUSTOMER phù hợp; với VNPay dùng sandbox. 3. Thực hiện: Cập nhật tăng/giảm số lượng bằng nút và nhập trực tiếp. 4. Ghi nhận UI, HTTP response, log và dữ liệu database liên quan. | D68: Thành tiền dòng/tổng dự kiến cập nhật; phải lưu trước checkout. | H68: 46310 | I68: Pass | J68: Ưu tiên: P1 Batch 1/3 - 15/10/2026 - Pass: qty 1->2; dirty=true; DB=2
A69: CART-06 | B69: Xóa một dòng và dòng cuối cùng. | C69: 1. Mở TechStore trên môi trường test. 2. Đăng nhập bằng tài khoản CUSTOMER phù hợp; với VNPay dùng sandbox. 3. Thực hiện: Xóa một dòng và dòng cuối cùng. 4. Ghi nhận UI, HTTP response, log và dữ liệu database liên quan. | D69: Dòng bị xóa; giỏ rỗng có empty state. | H69: 46310 | I69: Pass | J69: Ưu tiên: P1 Batch 1/3 - 15/10/2026 - Pass: after one=1; after last=0; emptyState=true
A70: CART-07 | B70: Khách A sửa request với variant trong giỏ Khách B. | C70: 1. Mở TechStore trên môi trường test. 2. Đăng nhập bằng tài khoản CUSTOMER phù hợp; với VNPay dùng sandbox. 3. Thực hiện: Khách A sửa request với variant trong giỏ Khách B. 4. Ghi nhận UI, HTTP response, log và dữ liệu database liên quan. | D70: Giỏ B không thay đổi. | H70: 46310 | I70: Pass | J70: Ưu tiên: P0 Batch 1/3 - 15/10/2026 - Pass: userB quantity=2->2
A71: CART-08 | B71: Admin giảm tồn kho dưới số lượng đang nằm trong giỏ rồi checkout. | C71: 1. Mở TechStore trên môi trường test. 2. Đăng nhập bằng tài khoản CUSTOMER phù hợp; với VNPay dùng sandbox. 3. Thực hiện: Admin giảm tồn kho dưới số lượng đang nằm trong giỏ rồi checkout. 4. Ghi nhận UI, HTTP response, log và dữ liệu database liên quan. | D71: Checkout chặn và không tạo đơn/trừ kho. | H71: 46310 | I71: Pass | J71: Ưu tiên: P0 Batch 1/3 - 15/10/2026 - Pass: orders=0->0; stock=1; blocked=true
A72: CART-09 | B72: Đổi giá sản phẩm sau khi đã thêm giỏ. | C72: 1. Mở TechStore trên môi trường test. 2. Đăng nhập bằng tài khoản CUSTOMER phù hợp; với VNPay dùng sandbox. 3. Thực hiện: Đổi giá sản phẩm sau khi đã thêm giỏ. 4. Ghi nhận UI, HTTP response, log và dữ liệu database liên quan. | D72: Giỏ/checkout dùng giá server hiện hành; không tin giá gửi từ client. | H72: 46310 | I72: Pass | J72: Ưu tiên: P1 Batch 1/3 - 15/10/2026 - Pass: Live flow đã đổi giá trực tiếp trong DB sau khi thêm giỏ rồi reload cart; CartServlet/CartItemDAO tải ProductVariant từ server, data-unit-price và checkout lấy giá hiện hành. Assertion cũ chỉ sai do kiểm tra chuỗi tiền theo locale.
A73: CART-10 | B73: Đặt hàng xong rồi mở giỏ. | C73: 1. Mở TechStore trên môi trường test. 2. Đăng nhập bằng tài khoản CUSTOMER phù hợp; với VNPay dùng sandbox. 3. Thực hiện: Đặt hàng xong rồi mở giỏ. 4. Ghi nhận UI, HTTP response, log và dữ liệu database liên quan. | D73: Giỏ cũ thành ORDERED, giỏ active mới/rỗng được dùng. | H73: 46310 | I73: Pass | J73: Ưu tiên: P1 Batch 1/3 - 15/10/2026 - Pass: redirect=http://localhost:8080/TechStore/orders/detail?code=TS202610151630240B3BDE; latestCart=ORDERED; activeItems=0
A74: 5.7. Hồ sơ và địa chỉ
A75: ACC-01 | B75: Sửa họ tên và số điện thoại hợp lệ. | C75: 1. Mở TechStore trên môi trường test. 2. Đăng nhập bằng tài khoản CUSTOMER phù hợp; với VNPay dùng sandbox. 3. Thực hiện: Sửa họ tên và số điện thoại hợp lệ. 4. Ghi nhận UI, HTTP response, log và dữ liệu database liên quan. | D75: Database và tên trên header/session cập nhật. | H75: 46310 | I75: Pass | J75: Ưu tiên: P1 Batch 1/3 - 15/10/2026 - Pass: POST hồ sơ thành công; header/session hiển thị tên mới và DB lưu phone 0901234568. Chuỗi tên SQL ở log bị mojibake do console sqlcmd, không phải dữ liệu web.
A76: ACC-02 | B76: Họ tên rỗng/quá 150 và điện thoại sai. | C76: 1. Mở TechStore trên môi trường test. 2. Đăng nhập bằng tài khoản CUSTOMER phù hợp; với VNPay dùng sandbox. 3. Thực hiện: Họ tên rỗng/quá 150 và điện thoại sai. 4. Ghi nhận UI, HTTP response, log và dữ liệu database liên quan. | D76: Bị từ chối, không ghi dữ liệu lỗi. | H76: 46310 | I76: Pass | J76: Ưu tiên: P1 Batch 1/3 - 15/10/2026 - Pass: validation=true; DB unchanged=true
A77: ACC-03 | B77: Đổi mật khẩu với mật khẩu hiện tại đúng. | C77: 1. Mở TechStore trên môi trường test. 2. Đăng nhập bằng tài khoản CUSTOMER phù hợp; với VNPay dùng sandbox. 3. Thực hiện: Đổi mật khẩu với mật khẩu hiện tại đúng. 4. Ghi nhận UI, HTTP response, log và dữ liệu database liên quan. | D77: Thành công, session ID đổi, đăng nhập bằng mật khẩu mới được. | H77: 46310 | I77: Pass | J77: Ưu tiên: P0 Batch 1/3 - 15/10/2026 - Pass: sessionChanged=true; newLogin=http://localhost:8080/TechStore/home
A78: ACC-04 | B78: Mật khẩu hiện tại sai, mật khẩu mới trùng cũ, xác nhận sai, dài 7/73. | C78: 1. Mở TechStore trên môi trường test. 2. Đăng nhập bằng tài khoản CUSTOMER phù hợp; với VNPay dùng sandbox. 3. Thực hiện: Mật khẩu hiện tại sai, mật khẩu mới trùng cũ, xác nhận sai, dài 7/73. 4. Ghi nhận UI, HTTP response, log và dữ liệu database liên quan. | D78: Bị từ chối đúng lý do, hash không đổi. | H78: 46310 | I78: Pass | J78: Ưu tiên: P0 Batch 1/3 - 15/10/2026 - Pass: all rejected=true; hash unchanged=true
A79: ADDR-01 | B79: Thêm địa chỉ đủ trường và điện thoại hợp lệ. | C79: 1. Mở TechStore trên môi trường test. 2. Đăng nhập bằng tài khoản CUSTOMER phù hợp; với VNPay dùng sandbox. 3. Thực hiện: Thêm địa chỉ đủ trường và điện thoại hợp lệ. 4. Ghi nhận UI, HTTP response, log và dữ liệu database liên quan. | D79: Địa chỉ được lưu cho đúng user. | H79: 46310 | I79: Pass | J79: Ưu tiên: P1 Batch 1/3 - 15/10/2026 - Pass: addressId=1; owner/phone=codex.batch1.20261015092634.userb@techstore.local|0901234569
A80: ADDR-02 | B80: Bỏ trống từng trường, vượt giới hạn và điện thoại sai. | C80: 1. Mở TechStore trên môi trường test. 2. Đăng nhập bằng tài khoản CUSTOMER phù hợp; với VNPay dùng sandbox. 3. Thực hiện: Bỏ trống từng trường, vượt giới hạn và điện thoại sai. 4. Ghi nhận UI, HTTP response, log và dữ liệu database liên quan. | D80: Hiển thị validation, không tạo dữ liệu rác. | H80: 46310 | I80: Pass | J80: Ưu tiên: P1 Batch 1/3 - 15/10/2026 - Pass: validation=true; rows=1->1
A81: ADDR-03 | B81: Sửa rồi xóa địa chỉ của chính mình. | C81: 1. Mở TechStore trên môi trường test. 2. Đăng nhập bằng tài khoản CUSTOMER phù hợp; với VNPay dùng sandbox. 3. Thực hiện: Sửa rồi xóa địa chỉ của chính mình. 4. Ghi nhận UI, HTTP response, log và dữ liệu database liên quan. | D81: Thay đổi đúng; danh sách và checkout cập nhật. | H81: 46310 | I81: Pass | J81: Ưu tiên: P1 Batch 1/3 - 15/10/2026 - Pass: Địa chỉ được cập nhật đúng district Q3/address line mới rồi xóa; số dòng AddressId sau xóa bằng 0. Dấu tiếng Việt chỉ mojibake tại output sqlcmd.
A82: ADDR-04 | B82: Đặt địa chỉ mặc định lần lượt cho hai địa chỉ. | C82: 1. Mở TechStore trên môi trường test. 2. Đăng nhập bằng tài khoản CUSTOMER phù hợp; với VNPay dùng sandbox. 3. Thực hiện: Đặt địa chỉ mặc định lần lượt cho hai địa chỉ. 4. Ghi nhận UI, HTTP response, log và dữ liệu database liên quan. | D82: Mỗi user chỉ có tối đa một địa chỉ mặc định. | H82: 46310 | I82: Pass | J82: Ưu tiên: P1 Batch 2/3 - 15/10/2026 - Pass: DefaultCount:Id=1:12
A83: ADDR-05 | B83: Khách A sửa/xóa/default địa chỉ của Khách B bằng ID thủ công. | C83: 1. Mở TechStore trên môi trường test. 2. Đăng nhập bằng tài khoản CUSTOMER phù hợp; với VNPay dùng sandbox. 3. Thực hiện: Khách A sửa/xóa/default địa chỉ của Khách B bằng ID thủ công. 4. Ghi nhận UI, HTTP response, log và dữ liệu database liên quan. | D83: Bị từ chối; dữ liệu B không đổi. | H83: 46310 | I83: Pass | J83: Ưu tiên: P0 Batch 2/3 - 15/10/2026 - Pass: B unchanged=True
A84: ADDR-06 | B84: Xóa địa chỉ mặc định rồi mở checkout. | C84: 1. Mở TechStore trên môi trường test. 2. Đăng nhập bằng tài khoản CUSTOMER phù hợp; với VNPay dùng sandbox. 3. Thực hiện: Xóa địa chỉ mặc định rồi mở checkout. 4. Ghi nhận UI, HTTP response, log và dữ liệu database liên quan. | D84: Không lỗi; chọn địa chỉ còn lại hoặc form nhập mới. | H84: 46310 | I84: Pass | J84: Ưu tiên: P1 Batch 2/3 - 15/10/2026 - Pass: HTTP=200; selectedRemaining=True
A85: 5.8. Checkout COD và tạo đơn
A86: CHK-01 | B86: Mở checkout khi chưa đăng nhập hoặc giỏ rỗng. | C86: 1. Mở TechStore trên môi trường test. 2. Đăng nhập bằng tài khoản CUSTOMER phù hợp; với VNPay dùng sandbox. 3. Thực hiện: Mở checkout khi chưa đăng nhập hoặc giỏ rỗng. 4. Ghi nhận UI, HTTP response, log và dữ liệu database liên quan. | D86: Chuyển login hoặc giỏ với thông báo phù hợp. | H86: 46310 | I86: Pass | J86: Ưu tiên: P0 Batch 2/3 - 15/10/2026 - Pass: guest=http://localhost:8080/TechStore/login; empty=http://localhost:8080/TechStore/cart
A87: CHK-02 | B87: Có địa chỉ mặc định rồi mở checkout. | C87: 1. Mở TechStore trên môi trường test. 2. Đăng nhập bằng tài khoản CUSTOMER phù hợp; với VNPay dùng sandbox. 3. Thực hiện: Có địa chỉ mặc định rồi mở checkout. 4. Ghi nhận UI, HTTP response, log và dữ liệu database liên quan. | D87: Tự chọn địa chỉ mặc định; nếu không có chọn địa chỉ đầu tiên/form mới. | H87: 46310 | I87: Pass | J87: Ưu tiên: P1 Batch 2/3 - 15/10/2026 - Pass: selected=11
A88: CHK-03 | B88: Chèn addressId của Khách B. | C88: 1. Mở TechStore trên môi trường test. 2. Đăng nhập bằng tài khoản CUSTOMER phù hợp; với VNPay dùng sandbox. 3. Thực hiện: Chèn addressId của Khách B. 4. Ghi nhận UI, HTTP response, log và dữ liệu database liên quan. | D88: Server bỏ/từ chối ID, không dùng địa chỉ B. | H88: 46310 | I88: Pass | J88: Ưu tiên: P0 Batch 2/3 - 15/10/2026 - Pass: orders=0->0
A89: CHK-04 | B89: Đặt COD bằng địa chỉ lưu hợp lệ. | C89: 1. Mở TechStore trên môi trường test. 2. Đăng nhập bằng tài khoản CUSTOMER phù hợp; với VNPay dùng sandbox. 3. Thực hiện: Đặt COD bằng địa chỉ lưu hợp lệ. 4. Ghi nhận UI, HTTP response, log và dữ liệu database liên quan. | D89: Tạo đơn PENDING, payment COD PENDING, chuyển chi tiết đơn. | H89: 46310 | I89: Pass | J89: Ưu tiên: P1 Batch 2/3 - 15/10/2026 - Pass: state=PENDING|COD|PENDING
A90: CHK-05 | B90: Đặt COD bằng địa chỉ nhập mới hợp lệ. | C90: 1. Mở TechStore trên môi trường test. 2. Đăng nhập bằng tài khoản CUSTOMER phù hợp; với VNPay dùng sandbox. 3. Thực hiện: Đặt COD bằng địa chỉ nhập mới hợp lệ. 4. Ghi nhận UI, HTTP response, log và dữ liệu database liên quan. | D90: Snapshot người nhận/địa chỉ đúng; không bắt buộc lưu vào sổ địa chỉ. | H90: 46310 | I90: Pass | J90: Ưu tiên: P1 Checkout COD bằng địa chỉ nhập mới tạo đơn thành công; order detail hiển thị mã đơn và dữ liệu nhận hàng.
A91: CHK-06 | B91: Sai từng trường địa chỉ và ghi chú trên 500 ký tự. | C91: 1. Mở TechStore trên môi trường test. 2. Đăng nhập bằng tài khoản CUSTOMER phù hợp; với VNPay dùng sandbox. 3. Thực hiện: Sai từng trường địa chỉ và ghi chú trên 500 ký tự. 4. Ghi nhận UI, HTTP response, log và dữ liệu database liên quan. | D91: Báo lỗi tại trường, không tạo đơn. | H91: 46310 | I91: Pass | J91: Ưu tiên: P1 Batch 2/3 - 15/10/2026 - Pass: 7 invalid field/note variants rejected=True
A92: CHK-07 | B92: Gửi payment method ngoài COD/VNPAY. | C92: 1. Mở TechStore trên môi trường test. 2. Đăng nhập bằng tài khoản CUSTOMER phù hợp; với VNPay dùng sandbox. 3. Thực hiện: Gửi payment method ngoài COD/VNPAY. 4. Ghi nhận UI, HTTP response, log và dữ liệu database liên quan. | D92: Bị từ chối phía server. | H92: 46310 | I92: Pass | J92: Ưu tiên: P0 Batch 2/3 - 15/10/2026 - Pass: orders=1->1
A93: CHK-08 | B93: Sửa HTML gửi giá, subtotal, discount hoặc shipping fee giả. | C93: 1. Mở TechStore trên môi trường test. 2. Đăng nhập bằng tài khoản CUSTOMER phù hợp; với VNPay dùng sandbox. 3. Thực hiện: Sửa HTML gửi giá, subtotal, discount hoặc shipping fee giả. 4. Ghi nhận UI, HTTP response, log và dữ liệu database liên quan. | D93: Tổng đơn vẫn do server tính; client không điều khiển được giá. | H93: 46310 | I93: Pass | J93: Ưu tiên: P0 Batch 2/3 - 15/10/2026 - Pass: server totals=200000|0|0|200000
A94: CHK-09 | B94: Nhấn submit hai lần/gửi lại cùng checkoutToken. | C94: 1. Mở TechStore trên môi trường test. 2. Đăng nhập bằng tài khoản CUSTOMER phù hợp; với VNPay dùng sandbox. 3. Thực hiện: Nhấn submit hai lần/gửi lại cùng checkoutToken. 4. Ghi nhận UI, HTTP response, log và dữ liệu database liên quan. | D94: Chỉ tạo một đơn; lần sau báo yêu cầu hết hiệu lực. | H94: 46310 | I94: Pass | J94: Ưu tiên: P0 Batch 2/3 - 15/10/2026 - Pass: orders=2->3
A95: CHK-10 | B95: Đặt hàng khi một SKU vừa hết kho. | C95: 1. Mở TechStore trên môi trường test. 2. Đăng nhập bằng tài khoản CUSTOMER phù hợp; với VNPay dùng sandbox. 3. Thực hiện: Đặt hàng khi một SKU vừa hết kho. 4. Ghi nhận UI, HTTP response, log và dữ liệu database liên quan. | D95: Toàn transaction rollback: không đơn rác, không payment/history rác, kho không âm. | H95: 46310 | I95: Pass | J95: Ưu tiên: P0 Batch 2/3 - 15/10/2026 - Pass: orders=3->3; stock=10|1
A96: CHK-11 | B96: Đặt đơn nhiều SKU hợp lệ. | C96: 1. Mở TechStore trên môi trường test. 2. Đăng nhập bằng tài khoản CUSTOMER phù hợp; với VNPay dùng sandbox. 3. Thực hiện: Đặt đơn nhiều SKU hợp lệ. 4. Ghi nhận UI, HTTP response, log và dữ liệu database liên quan. | D96: Từng line total, subtotal, total và số lượng kho đều chính xác. | H96: 46310 | I96: Pass | J96: Ưu tiên: P0 Batch 2/3 - 15/10/2026 - Pass: lines|sum|subtotal|stocks=2|950000|950000|18|17
A97: CHK-12 | B97: Đối chiếu sau đặt đơn. | C97: 1. Mở TechStore trên môi trường test. 2. Đăng nhập bằng tài khoản CUSTOMER phù hợp; với VNPay dùng sandbox. 3. Thực hiện: Đối chiếu sau đặt đơn. 4. Ghi nhận UI, HTTP response, log và dữ liệu database liên quan. | D97: Có Order, OrderItems snapshot, Payment, history PENDING; cart thành ORDERED. | H97: 46310 | I97: Pass | J97: Ưu tiên: P0 SQL đối chiếu Order, OrderItems, Payment, tổng tiền và tồn kho sau đặt hàng; hủy test hoàn kho đúng.
A98: 5.9. Lịch sử, chi tiết và hủy đơn
A99: ORD-01 | B99: Mở lịch sử có trên 20 đơn và đổi trang. | C99: 1. Mở TechStore trên môi trường test. 2. Đăng nhập bằng tài khoản CUSTOMER phù hợp; với VNPay dùng sandbox. 3. Thực hiện: Mở lịch sử có trên 20 đơn và đổi trang. 4. Ghi nhận UI, HTTP response, log và dữ liệu database liên quan. | D99: Đúng user, mới trước, phân trang không trùng/mất đơn. | H99: 46310 | I99: Pass | J99: Ưu tiên: P1 Batch 2/3 - 15/10/2026 - Pass: testOrders page1=16;page2=5;total=21;overlap=0
A100: ORD-02 | B100: Mở chi tiết mã đơn hợp lệ/sai. | C100: 1. Mở TechStore trên môi trường test. 2. Đăng nhập bằng tài khoản CUSTOMER phù hợp; với VNPay dùng sandbox. 3. Thực hiện: Mở chi tiết mã đơn hợp lệ/sai. 4. Ghi nhận UI, HTTP response, log và dữ liệu database liên quan. | D100: Hợp lệ hiển thị đầy đủ; sai trả 404. | H100: 46310 | I100: Pass | J100: Ưu tiên: P1 Batch 2/3 - 15/10/2026 - Pass: valid=200;invalid=404
A101: ORD-03 | B101: Khách B mở mã đơn của Khách A. | C101: 1. Mở TechStore trên môi trường test. 2. Đăng nhập bằng tài khoản CUSTOMER phù hợp; với VNPay dùng sandbox. 3. Thực hiện: Khách B mở mã đơn của Khách A. 4. Ghi nhận UI, HTTP response, log và dữ liệu database liên quan. | D101: HTTP 403, không lộ dữ liệu đơn. | H101: 46310 | I101: Pass | J101: Ưu tiên: P0 Tài khoản thứ hai mở chi tiết đơn của tài khoản test nhận HTTP 403.
A102: ORD-04 | B102: Đối chiếu sản phẩm, snapshot SKU/giá/ảnh, tổng, địa chỉ, timeline. | C102: 1. Mở TechStore trên môi trường test. 2. Đăng nhập bằng tài khoản CUSTOMER phù hợp; với VNPay dùng sandbox. 3. Thực hiện: Đối chiếu sản phẩm, snapshot SKU/giá/ảnh, tổng, địa chỉ, timeline. 4. Ghi nhận UI, HTTP response, log và dữ liệu database liên quan. | D102: Khớp dữ liệu tại lúc đặt hàng. | H102: 46310 | I102: Pass | J102: Ưu tiên: P1 Batch 2/3 - 15/10/2026 - Pass: SQL=2|950000|950000|1; status=200;skuA=True;skuB=True;total=True
A103: ORD-05 | B103: Khách hủy đơn PENDING/CONFIRMED/PROCESSING chưa thanh toán, có lý do. | C103: 1. Mở TechStore trên môi trường test. 2. Đăng nhập bằng tài khoản CUSTOMER phù hợp; với VNPay dùng sandbox. 3. Thực hiện: Khách hủy đơn PENDING/CONFIRMED/PROCESSING chưa thanh toán, có lý do. 4. Ghi nhận UI, HTTP response, log và dữ liệu database liên quan. | D103: Đơn CANCELLED, payment thất bại, lịch sử có lý do, kho hoàn đúng một lần. | H103: 46310 | I103: Pass | J103: Ưu tiên: P0 Batch 2/3 - 15/10/2026 - Pass: CANCELLED|FAILED|FAILED|10|1;CANCELLED|FAILED|FAILED|10|1;CANCELLED|FAILED|FAILED|10|1
A104: ORD-06 | B104: Hủy không có lý do hoặc quá 500 ký tự. | C104: 1. Mở TechStore trên môi trường test. 2. Đăng nhập bằng tài khoản CUSTOMER phù hợp; với VNPay dùng sandbox. 3. Thực hiện: Hủy không có lý do hoặc quá 500 ký tự. 4. Ghi nhận UI, HTTP response, log và dữ liệu database liên quan. | D104: Bị từ chối. | H104: 46310 | I104: Pass | J104: Ưu tiên: P0 Batch 2/3 - 15/10/2026 - Pass: blank and 501-char reasons rejected=True
A105: ORD-07 | B105: Hủy lại đơn đã hủy; hủy SHIPPING/COMPLETED. | C105: 1. Mở TechStore trên môi trường test. 2. Đăng nhập bằng tài khoản CUSTOMER phù hợp; với VNPay dùng sandbox. 3. Thực hiện: Hủy lại đơn đã hủy; hủy SHIPPING/COMPLETED. 4. Ghi nhận UI, HTTP response, log và dữ liệu database liên quan. | D105: Bị từ chối, kho không hoàn thêm. | H105: 46310 | I105: Pass | J105: Ưu tiên: P0 Batch 2/3 - 15/10/2026 - Pass: shipping/completed blocked=True; repeated stock=10
A106: ORD-08 | B106: Hủy đơn PAID. | C106: 1. Mở TechStore trên môi trường test. 2. Đăng nhập bằng tài khoản CUSTOMER phù hợp; với VNPay dùng sandbox. 3. Thực hiện: Hủy đơn PAID. 4. Ghi nhận UI, HTTP response, log và dữ liệu database liên quan. | D106: Bị từ chối và hướng dẫn xử lý hoàn tiền. | H106: 46310 | I106: Pass | J106: Ưu tiên: P0 Batch 2/3 - 15/10/2026 - Pass: state=PENDING|PAID|9
...

Sheet Test Report
A1: TEST REPORT
B3: Note: | C3: 15/10/2026: Hoàn tất đợt 3/3 (50 test case): 45 Pass, 5 Fail. Tổng kết quả: 179 Pass, 9 Fail, 0 Pending. Đã kiểm tra admin, security, transaction, database, UI/accessibility, hiệu năng và deploy; dữ liệu test tạm được dọn sau khi ghi nhận.
B4: Date | C4: 46310
B7: No | C7: Module code | D7: Pass | E7: Fail | F7: Pending | G7: Number of test cases
B8: 1 | C8: 5.1 - Hệ thống và điều hướng | D8: =COUNTIF('TechStore Test Cases'!I13:I18,"Pass") -> 6 | E8: =COUNTIF('TechStore Test Cases'!I13:I18,"Fail") -> 0 | F8: =COUNTIF('TechStore Test Cases'!I13:I18,"Pending") -> 0 | G8: =COUNTA('TechStore Test Cases'!A13:A18) -> 6
B9: 2 | C9: 5.2 - Đăng ký, đăng nhập và session | D9: =COUNTIF('TechStore Test Cases'!I20:I34,"Pass") -> 15 | E9: =COUNTIF('TechStore Test Cases'!I20:I34,"Fail") -> 0 | F9: =COUNTIF('TechStore Test Cases'!I20:I34,"Pending") -> 0 | G9: =COUNTA('TechStore Test Cases'!A20:A34) -> 15
B10: 3 | C10: 5.3 - Quên và đặt lại mật khẩu | D10: =COUNTIF('TechStore Test Cases'!I36:I43,"Pass") -> 8 | E10: =COUNTIF('TechStore Test Cases'!I36:I43,"Fail") -> 0 | F10: =COUNTIF('TechStore Test Cases'!I36:I43,"Pending") -> 0 | G10: =COUNTA('TechStore Test Cases'!A36:A43) -> 8
B11: 4 | C11: 5.4 - Trang chủ, catalog và chi tiết sản phẩm | D11: =COUNTIF('TechStore Test Cases'!I45:I56,"Pass") -> 11 | E11: =COUNTIF('TechStore Test Cases'!I45:I56,"Fail") -> 1 | F11: =COUNTIF('TechStore Test Cases'!I45:I56,"Pending") -> 0 | G11: =COUNTA('TechStore Test Cases'!A45:A56) -> 12
B12: 5 | C12: 5.5 - Yêu thích | D12: =COUNTIF('TechStore Test Cases'!I58:I62,"Pass") -> 4 | E12: =COUNTIF('TechStore Test Cases'!I58:I62,"Fail") -> 1 | F12: =COUNTIF('TechStore Test Cases'!I58:I62,"Pending") -> 0 | G12: =COUNTA('TechStore Test Cases'!A58:A62) -> 5
B13: 6 | C13: 5.6 - Giỏ hàng | D13: =COUNTIF('TechStore Test Cases'!I64:I73,"Pass") -> 10 | E13: =COUNTIF('TechStore Test Cases'!I64:I73,"Fail") -> 0 | F13: =COUNTIF('TechStore Test Cases'!I64:I73,"Pending") -> 0 | G13: =COUNTA('TechStore Test Cases'!A64:A73) -> 10
B14: 7 | C14: 5.7 - Hồ sơ và địa chỉ | D14: =COUNTIF('TechStore Test Cases'!I75:I84,"Pass") -> 10 | E14: =COUNTIF('TechStore Test Cases'!I75:I84,"Fail") -> 0 | F14: =COUNTIF('TechStore Test Cases'!I75:I84,"Pending") -> 0 | G14: =COUNTA('TechStore Test Cases'!A75:A84) -> 10
B15: 8 | C15: 5.8 - Checkout COD và tạo đơn | D15: =COUNTIF('TechStore Test Cases'!I86:I97,"Pass") -> 12 | E15: =COUNTIF('TechStore Test Cases'!I86:I97,"Fail") -> 0 | F15: =COUNTIF('TechStore Test Cases'!I86:I97,"Pending") -> 0 | G15: =COUNTA('TechStore Test Cases'!A86:A97) -> 12
B16: 9 | C16: 5.9 - Lịch sử, chi tiết và hủy đơn | D16: =COUNTIF('TechStore Test Cases'!I99:I108,"Pass") -> 10 | E16: =COUNTIF('TechStore Test Cases'!I99:I108,"Fail") -> 0 | F16: =COUNTIF('TechStore Test Cases'!I99:I108,"Pending") -> 0 | G16: =COUNTA('TechStore Test Cases'!A99:A108) -> 10
B17: 10 | C17: 5.10 - VNPay sandbox | D17: =COUNTIF('TechStore Test Cases'!I110:I123,"Pass") -> 13 | E17: =COUNTIF('TechStore Test Cases'!I110:I123,"Fail") -> 1 | F17: =COUNTIF('TechStore Test Cases'!I110:I123,"Pending") -> 0 | G17: =COUNTA('TechStore Test Cases'!A110:A123) -> 14
B18: 11 | C18: 5.11 - Admin dashboard và báo cáo | D18: =COUNTIF('TechStore Test Cases'!I125:I132,"Pass") -> 8 | E18: =COUNTIF('TechStore Test Cases'!I125:I132,"Fail") -> 0 | F18: =COUNTIF('TechStore Test Cases'!I125:I132,"Pending") -> 0 | G18: =COUNTA('TechStore Test Cases'!A125:A132) -> 8
B19: 12 | C19: 5.12 - Admin catalog, sản phẩm và tài sản | D19: =COUNTIF('TechStore Test Cases'!I134:I157,"Pass") -> 24 | E19: =COUNTIF('TechStore Test Cases'!I134:I157,"Fail") -> 0 | F19: =COUNTIF('TechStore Test Cases'!I134:I157,"Pending") -> 0 | G19: =COUNTA('TechStore Test Cases'!A134:A157) -> 24
B20: 13 | C20: 5.13 - Admin đơn hàng và người dùng | D20: =COUNTIF('TechStore Test Cases'!I159:I171,"Pass") -> 13 | E20: =COUNTIF('TechStore Test Cases'!I159:I171,"Fail") -> 0 | F20: =COUNTIF('TechStore Test Cases'!I159:I171,"Pending") -> 0 | G20: =COUNTA('TechStore Test Cases'!A159:A171) -> 13
B21: 14 | C21: 6.1 - CSRF, session, quyền và dữ liệu đầu vào | D21: =COUNTIF('TechStore Test Cases'!I173:I184,"Pass") -> 9 | E21: =COUNTIF('TechStore Test Cases'!I173:I184,"Fail") -> 3 | F21: =COUNTIF('TechStore Test Cases'!I173:I184,"Pending") -> 0 | G21: =COUNTA('TechStore Test Cases'!A173:A184) -> 12
B22: 15 | C22: 6.2 - Database, transaction và cạnh tranh | D22: =COUNTIF('TechStore Test Cases'!I186:I193,"Pass") -> 7 | E22: =COUNTIF('TechStore Test Cases'!I186:I193,"Fail") -> 1 | F22: =COUNTIF('TechStore Test Cases'!I186:I193,"Pending") -> 0 | G22: =COUNTA('TechStore Test Cases'!A186:A193) -> 8
B23: 16 | C23: 6.3 - Responsive, trình duyệt và accessibility | D23: =COUNTIF('TechStore Test Cases'!I195:I205,"Pass") -> 10 | E23: =COUNTIF('TechStore Test Cases'!I195:I205,"Fail") -> 1 | F23: =COUNTIF('TechStore Test Cases'!I195:I205,"Pending") -> 0 | G23: =COUNTA('TechStore Test Cases'!A195:A205) -> 11
B24: 17 | C24: 6.4 - Hiệu năng, ổn định và deploy | D24: =COUNTIF('TechStore Test Cases'!I207:I216,"Pass") -> 9 | E24: =COUNTIF('TechStore Test Cases'!I207:I216,"Fail") -> 1 | F24: =COUNTIF('TechStore Test Cases'!I207:I216,"Pending") -> 0 | G24: =COUNTA('TechStore Test Cases'!A207:A216) -> 10
C26: Sub total | D26: =SUM(D8:D24) -> 179 | E26: =SUM(E8:E24) -> 9 | F26: =SUM(F8:F24) -> 0 | G26: =SUM(G8:G24) -> 188
C28: Test coverage | E28: =IF(G26=0,0,(D26+E26)*100/G26) -> 100 | F28: %
C29: Test successful coverage | E29: =IF(G26=0,0,D26*100/G26) -> 95.212766 | F29: %
